behave_dock/__init__.py
behave_dock/adapters/__init__.py
behave_dock/adapters/api.py
behave_dock/adapters/base.py
behave_dock/adapters/kafka.py
behave_dock/behave_link.py
behave_dock/blueprints/__init__.py
behave_dock/blueprints/base.py
behave_dock/blueprints/kafka.py
behave_dock/blueprints/postgresql.py
behave_dock/blueprints/rabbitmq.py
behave_dock/blueprints/redis.py
behave_dock/blueprints/schema_registry.py
behave_dock/dependency_injector.py
behave_dock/environment.py
behave_dock/exceptions.py
behave_dock/providers/__init__.py
behave_dock/providers/docker/__init__.py
behave_dock/providers/docker/base.py
behave_dock/providers/docker/kafka.py
behave_dock/providers/docker/postgresql.py
behave_dock/providers/docker/rabbitmq.py
behave_dock/providers/docker/redis.py
behave_dock/providers/docker/schema_registry.py
behave_dock/py.typed
behave_dock/sandbox.py
behave_dock/utils/__init__.py
behave_dock/utils/exec.py
behave_dock-0.1.0.dist-info/METADATA
behave_dock-0.1.0.dist-info/WHEEL
behave_dock-0.1.0.dist-info/licenses/LICENSE.txt
behave_dock-0.1.0.dist-info/RECORD
