Metadata-Version: 2.4
Name: behave-dock
Version: 0.1.0
Summary: A dead-simple end-to-end testing tool for containerized microservices and monoliths, based on the Python Behave library.
License-Expression: MIT
License-File: LICENSE.txt
Keywords: behave,BDD,docker,orchestration
Author: M. Hosseyn Najafi
Author-email: hosseynjf@icloud.com
Requires-Python: >=3.10,<4.0
Classifier: Development Status :: 4 - Beta
Classifier: Intended Audience :: Developers
Classifier: Topic :: Software Development :: Libraries :: Python Modules
Classifier: Topic :: Software Development :: Quality Assurance
Classifier: Topic :: Software Development :: Testing :: Acceptance
Classifier: Topic :: Software Development :: Testing :: BDD
Classifier: Programming Language :: Python :: 3.10
Classifier: Programming Language :: Python :: 3.11
Classifier: Programming Language :: Python :: 3.12
Classifier: Programming Language :: Python :: 3.13
Classifier: Programming Language :: Python :: 3.14
Classifier: License :: OSI Approved :: MIT License
Classifier: Typing :: Typed
Requires-Dist: behave (>=1.2.6,<2.0.0)
Requires-Dist: kafka-python (>=2.0.0,<3.0.0)
Requires-Dist: kafka-schema-registry (>=0.1.0,<1.0.0)
Requires-Dist: psycopg2-binary (>=2.9.6,<3.0.0)
Requires-Dist: requests (>=2.31.0,<3.0.0)
Requires-Dist: requests-toolbelt (>=1.0.0,<2.0.0)
Requires-Dist: testcontainers[kafka,postgresql,rabbitmq,redis] (>=4.0.0,<5.0.0)
Project-URL: Changelog, https://github.com/HosseyNJF/behave-dock/blob/main/CHANGELOG.md
Project-URL: Homepage, https://github.com/HosseyNJF/behave-dock
Project-URL: Issues, https://github.com/HosseyNJF/behave-dock/issues
Project-URL: Repository, https://github.com/HosseyNJF/behave-dock.git
